ctags_mcp/__init__.py
ctags_mcp/ctags_parser.py
ctags_mcp/ctags_server.py
ctags_mcp/main.py
ctags_mcp/symbol_search.py
ctags_mcp-1.0.0.dist-info/METADATA
ctags_mcp-1.0.0.dist-info/WHEEL
ctags_mcp-1.0.0.dist-info/entry_points.txt
ctags_mcp-1.0.0.dist-info/licenses/LICENSE
ctags_mcp-1.0.0.dist-info/RECORD
