Metadata-Version: 2.4
Name: ctags-mcp
Version: 1.0.0
Summary: MCP server for ctags-based code navigation in Claude Code
Project-URL: Homepage, https://github.com/gladiatr72/mcp-ctags
Project-URL: Repository, https://github.com/gladiatr72/mcp-ctags
Project-URL: Issues, https://github.com/gladiatr72/mcp-ctags/issues
License: MIT License
License-File: LICENSE
Keywords: ai,claude,code-navigation,ctags,mcp
Classifier: Development Status :: 4 - Beta
Classifier: Intended Audience :: Developers
Classifier: License :: OSI Approved :: MIT License
Classifier: Programming Language :: Python :: 3
Classifier: Programming Language :: Python :: 3.10
Classifier: Programming Language :: Python :: 3.11
Classifier: Programming Language :: Python :: 3.12
Classifier: Programming Language :: Python :: 3.13
Classifier: Topic :: Software Development :: Libraries :: Python Modules
Classifier: Topic :: Text Editors :: Integrated Development Environments (IDE)
Requires-Python: >=3.10
Requires-Dist: mcp[cli]>=1.2.0
Requires-Dist: pydantic>=2.0.0
Requires-Dist: watchfiles>=0.21.0
Provides-Extra: dev
Requires-Dist: mypy>=1.0.0; extra == 'dev'
Requires-Dist: pytest>=8.0.0; extra == 'dev'
Requires-Dist: ruff>=0.1.0; extra == 'dev'
